NumpyJichuzhishiChuyi/README.md
NumpyJichuzhishiChuyi/__init__.py
NumpyJichuzhishiChuyi/__main__.py
NumpyJichuzhishiChuyi/file.epub
NumpyJichuzhishiChuyi/index.html
NumpyJichuzhishiChuyi/css/__init__.py
NumpyJichuzhishiChuyi/css/annotations.css
NumpyJichuzhishiChuyi/css/main.css
NumpyJichuzhishiChuyi/css/normalize.css
NumpyJichuzhishiChuyi/css/popup.css
NumpyJichuzhishiChuyi/font/__init__.py
NumpyJichuzhishiChuyi/font/fontello.eot
NumpyJichuzhishiChuyi/font/fontello.svg
NumpyJichuzhishiChuyi/font/fontello.ttf
NumpyJichuzhishiChuyi/font/fontello.woff
NumpyJichuzhishiChuyi/img/__init__.py
NumpyJichuzhishiChuyi/img/annotator-glyph-sprite.png
NumpyJichuzhishiChuyi/img/annotator-icon-sprite.png
NumpyJichuzhishiChuyi/img/apple-touch-icon.png
NumpyJichuzhishiChuyi/img/cancelfullscreen.png
NumpyJichuzhishiChuyi/img/close.png
NumpyJichuzhishiChuyi/img/fullscreen.png
NumpyJichuzhishiChuyi/img/loader.gif
NumpyJichuzhishiChuyi/img/menu-icon.png
NumpyJichuzhishiChuyi/img/save.png
NumpyJichuzhishiChuyi/img/saved.png
NumpyJichuzhishiChuyi/img/settings-s.png
NumpyJichuzhishiChuyi/img/settings.png
NumpyJichuzhishiChuyi/img/star.png
NumpyJichuzhishiChuyi/js/__init__.py
NumpyJichuzhishiChuyi/js/epub.js
NumpyJichuzhishiChuyi/js/epub.min.js
NumpyJichuzhishiChuyi/js/epub.min.map
NumpyJichuzhishiChuyi/js/hooks.min.js
NumpyJichuzhishiChuyi/js/hooks.min.map
NumpyJichuzhishiChuyi/js/reader.js
NumpyJichuzhishiChuyi/js/reader.js.map
NumpyJichuzhishiChuyi/js/reader.min.js
NumpyJichuzhishiChuyi/js/reader.min.map
NumpyJichuzhishiChuyi/js/hooks/__init__.py
NumpyJichuzhishiChuyi/js/hooks/extensions/__init__.py
NumpyJichuzhishiChuyi/js/hooks/extensions/highlight.js
NumpyJichuzhishiChuyi/js/libs/__init__.py
NumpyJichuzhishiChuyi/js/libs/jquery.min.js
NumpyJichuzhishiChuyi/js/libs/localforage.min.js
NumpyJichuzhishiChuyi/js/libs/screenfull.js
NumpyJichuzhishiChuyi/js/libs/screenfull.min.js
NumpyJichuzhishiChuyi/js/libs/zip.min.js
NumpyJichuzhishiChuyi/js/plugins/__init__.py
numpy_jichuzhishi_chuyi-2024.3.5.0.dist-info/METADATA
numpy_jichuzhishi_chuyi-2024.3.5.0.dist-info/WHEEL
numpy_jichuzhishi_chuyi-2024.3.5.0.dist-info/entry_points.txt
numpy_jichuzhishi_chuyi-2024.3.5.0.dist-info/top_level.txt
numpy_jichuzhishi_chuyi-2024.3.5.0.dist-info/RECORD
